mobizon_client/__init__.py
mobizon_client/client.py
mobizon_client/exceptions.py
mobizon_client/objects.py
mobizon_client-0.1.2.dist-info/WHEEL
mobizon_client-0.1.2.dist-info/METADATA
mobizon_client-0.1.2.dist-info/RECORD
