Metadata-Version: 2.1
Name: mobizon-client
Version: 0.1.2
Summary: 
Home-page: https://github.com/devstsoy/mobizon-client
Author: Stanislav Tsoy
Author-email: dev.stanislav@gmail.com
Requires-Python: >=3.10,<4.0
Classifier: Programming Language :: Python :: 3
Classifier: Programming Language :: Python :: 3.10
Classifier: Programming Language :: Python :: 3.11
Requires-Dist: httpx (>=0.23.3,<0.24.0)
Project-URL: Repository, https://github.com/devstsoy/mobizon-client
